nonebot_plugin_params/__init__.py
nonebot_plugin_params/consts.py
nonebot_plugin_params/deps.py
nonebot_plugin_params/exception.py
nonebot_plugin_params/permission.py
nonebot_plugin_params/py.typed
nonebot_plugin_params/rule.py
nonebot_plugin_params-0.1.1.dist-info/WHEEL
nonebot_plugin_params-0.1.1.dist-info/METADATA
nonebot_plugin_params-0.1.1.dist-info/license_files/LICENSE
nonebot_plugin_params-0.1.1.dist-info/RECORD
