Metadata-Version: 2.1
Name: nonebot-plugin-params
Version: 0.1.1
Summary: 提供协议适配时常用的注入函数
License: MIT
Author-email: iyume <iyumelive@gmail.com>
Requires-Python: >=3.7.3
Requires-Dist: nonebot2>=2.0.0b1
Requires-Dist: typing-extensions<5.0.0,>=3.10.0
Project-URL: Homepage, https://github.com/iyume/nonebot-plugin-params
Project-URL: repository, https://github.com/iyume/nonebot-plugin-params
